crackq_client/__init__.py
crackq_client/client.py
crackq_client/client_rest.py
crackq_client-0.0.1.dist-info/LICENCE.txt
crackq_client-0.0.1.dist-info/METADATA
crackq_client-0.0.1.dist-info/WHEEL
crackq_client-0.0.1.dist-info/entry_points.txt
crackq_client-0.0.1.dist-info/top_level.txt
crackq_client-0.0.1.dist-info/RECORD
