Metadata-Version: 2.1
Name: crackq-client
Version: 0.0.1
Summary: RESTful client for CrackQ
Home-page: https://github.com/f0cker/crackq_client
Author: Daniel Turner
License: UNKNOWN
Platform: UNKNOWN
Classifier: Programming Language :: Python :: 3
Classifier: License :: OSI Approved :: MIT License
Classifier: Operating System :: POSIX
Classifier: Operating System :: MacOS
Requires-Dist: idna (>=2.8)
Requires-Dist: requests (>=2.22.0)
